<?xml version="1.0" encoding="ISO-8859-1"?>
<scripts xmlns:xsi="http://www.w3.org/2001/XMLSchema-instance"
         xsi:noNamespaceSchemaLocation="../.gradle/scripts.xsd">

    <!-- 1. CREATE TABLE somente com PK e constraint -->
    <sql nomeTabela="THGQMGREG" ordem="1" executar="SE_NAO_EXISTIR"
         tipoObjeto="TABLE" nomeObjeto="THGQMGREG"
         descricao="Criacao da tabela THGQMGREG">
        <mssql>
            CREATE TABLE THGQMGREG (
            CODRNC INT NOT NULL,
            CONSTRAINT PK_THGQMGREG PRIMARY KEY (CODRNC)
            )
        </mssql>
        <oracle>
            CREATE TABLE THGQMGREG (
            CODRNC NUMBER(10) NOT NULL,
            CONSTRAINT PK_THGQMGREG PRIMARY KEY (CODRNC)
            )
        </oracle>
    </sql>

    <!-- 2. ALTER TABLE para cada coluna nao-PK -->
    <sql nomeTabela="THGQMGREG" ordem="2" executar="SE_NAO_EXISTIR"
         tipoObjeto="COLUMN" nomeObjeto="NURNC"
         descricao="Adicionar campo NURNC na tabela THGQMGREG">
        <mssql>
            ALTER TABLE THGQMGREG ADD NURNC INT
        </mssql>
        <oracle>
            ALTER TABLE THGQMGREG ADD (NURNC NUMBER(10))
        </oracle>
    </sql>

    <sql nomeTabela="THGQMGREG" ordem="3" executar="SE_NAO_EXISTIR"
         tipoObjeto="COLUMN" nomeObjeto="STATUS"
         descricao="Adicionar campo STATUS na tabela THGQMGREG">
        <mssql>
            ALTER TABLE THGQMGREG ADD STATUS VARCHAR(20)
        </mssql>
        <oracle>
            ALTER TABLE THGQMGREG ADD (STATUS VARCHAR2(20))
        </oracle>
    </sql>

    <sql nomeTabela="THGQMGREG" ordem="4" executar="SE_NAO_EXISTIR"
         tipoObjeto="COLUMN" nomeObjeto="FASEATUAL"
         descricao="Adicionar campo FASEATUAL na tabela THGQMGREG">
        <mssql>
            ALTER TABLE THGQMGREG ADD FASEATUAL VARCHAR(1)
        </mssql>
        <oracle>
            ALTER TABLE THGQMGREG ADD (FASEATUAL VARCHAR2(1))
        </oracle>
    </sql>

    <sql nomeTabela="THGQMGREG" ordem="5" executar="SE_NAO_EXISTIR"
         tipoObjeto="COLUMN" nomeObjeto="ORIGEM"
         descricao="Adicionar campo ORIGEM na tabela THGQMGREG">
        <mssql>
            ALTER TABLE THGQMGREG ADD ORIGEM VARCHAR(1)
        </mssql>
        <oracle>
            ALTER TABLE THGQMGREG ADD (ORIGEM VARCHAR2(1))
        </oracle>
    </sql>

    <sql nomeTabela="THGQMGREG" ordem="6" executar="SE_NAO_EXISTIR"
         tipoObjeto="COLUMN" nomeObjeto="CODPARC"
         descricao="Adicionar campo CODPARC na tabela THGQMGREG">
        <mssql>
            ALTER TABLE THGQMGREG ADD CODPARC INT
        </mssql>
        <oracle>
            ALTER TABLE THGQMGREG ADD (CODPARC NUMBER(10))
        </oracle>
    </sql>

    <sql nomeTabela="THGQMGREG" ordem="7" executar="SE_NAO_EXISTIR"
         tipoObjeto="COLUMN" nomeObjeto="CODUSU"
         descricao="Adicionar campo CODUSU na tabela THGQMGREG">
        <mssql>
            ALTER TABLE THGQMGREG ADD CODUSU INT
        </mssql>
        <oracle>
            ALTER TABLE THGQMGREG ADD (CODUSU NUMBER(10))
        </oracle>
    </sql>

    <sql nomeTabela="THGQMGREG" ordem="8" executar="SE_NAO_EXISTIR"
         tipoObjeto="COLUMN" nomeObjeto="DHALTER"
         descricao="Adicionar campo DHALTER na tabela THGQMGREG">
        <mssql>
            ALTER TABLE THGQMGREG ADD DHALTER DATETIME
        </mssql>
        <oracle>
            ALTER TABLE THGQMGREG ADD (DHALTER DATE)
        </oracle>
    </sql>

    <sql nomeTabela="THGQMGREG" ordem="9" executar="SE_NAO_EXISTIR"
         tipoObjeto="COLUMN" nomeObjeto="DHCREATE"
         descricao="Adicionar campo DHCREATE na tabela THGQMGREG">
        <mssql>
            ALTER TABLE THGQMGREG ADD DHCREATE DATETIME
        </mssql>
        <oracle>
            ALTER TABLE THGQMGREG ADD (DHCREATE DATE)
        </oracle>
    </sql>

    <sql nomeTabela="THGQMGREG" ordem="10" executar="SE_NAO_EXISTIR"
         tipoObjeto="COLUMN" nomeObjeto="ATIVO"
         descricao="Adicionar campo ATIVO na tabela THGQMGREG">
        <mssql>
            ALTER TABLE THGQMGREG ADD ATIVO CHAR(1)
        </mssql>
        <oracle>
            ALTER TABLE THGQMGREG ADD (ATIVO CHAR(1))
        </oracle>
    </sql>

</scripts>
